Metadata-Version: 2.1
Name: scCyclone
Version: 1.0.3
Summary: Single-Cell Cyclone Analysis Package
Home-page: https://github.com/dawangran/scCyclone
Author: Dawn
Author-email: 605547565@qq.com
Classifier: Programming Language :: Python :: 3
Classifier: License :: OSI Approved :: MIT License
Classifier: Operating System :: OS Independent
Requires-Python: >=3.8
License-File: LICENSE
